dojot_flow_node/__init__.py
dojot_flow_node/data_handler_base.py
dojot_flow_node/dojot_handler.py
dojot_flow_node-0.0.10.dist-info/DESCRIPTION.rst
dojot_flow_node-0.0.10.dist-info/METADATA
dojot_flow_node-0.0.10.dist-info/RECORD
dojot_flow_node-0.0.10.dist-info/WHEEL
dojot_flow_node-0.0.10.dist-info/metadata.json
dojot_flow_node-0.0.10.dist-info/top_level.txt
