Metadata-Version: 2.0
Name: dojot-flow-node
Version: 0.0.10
Summary: Dojot flow node.
Home-page: http://dojot.com.br
Author: Fabio Beranizo Fontes Lopes
Author-email: fabiol@cpqd.com.br
License: UNKNOWN
Platform: UNKNOWN
Requires-Dist: pyzmq
